Workbook
Name eur: 'Planned M&R Daily Report'!$I$17
Name eur: 'Planned M&R Project Plan'!$I$16
Name gbp: 'Planned M&R Daily Report'!$I$28
Name gbp: 'Planned M&R Project Plan'!$I$27
Name s00a: #REF!
Name s00b: #REF!
Name s00c: #REF!
Name s00d: #REF!
Name s00e: #REF!
Name s00f: #REF!
Name s00g: #REF!
Name s00h: #REF!
Name s00i: #REF!
Name s00j: #REF!
Name s00k: #REF!
Name s00k: #REF!
Name s00k: #REF!
Name s00k: #REF!
Name s00k: #REF!
Name s00k: #REF!
Name s00k: #REF!
Name s00k: #REF!
Name s00k: #REF!
Name s00k: #REF!
Name s00k: #REF!
Name s00k: #REF!
Name s00k: #REF!
Name s00l: #REF!
Name s00l: #REF!
Name s00l: #REF!
Name s00l: #REF!
Name s00l: #REF!
Name s00l: #REF!
Name s00l: #REF!
Name s00l: #REF!
Name s00l: #REF!
Name s00l: #REF!
Name s00l: #REF!
Name s00l: #REF!
Name s00l: #REF!
Name s00m: #REF!
Name s00m: #REF!
Name s00m: #REF!
Name s00m: #REF!
Name s00m: #REF!
Name s00m: #REF!
Name s00m: #REF!
Name s00m: #REF!
Name s00m: #REF!
Name s00m: #REF!
Name s00m: #REF!
Name s00m: #REF!
Name s00m: #REF!
Name s00n: #REF!
Name s00n: #REF!
Name s00n: #REF!
Name s00n: #REF!
Name s00n: #REF!
Name s00n: #REF!
Name s00n: #REF!

Sheet Instructions
A1: Instructions Planned M&R Budget Control Tool
A3: 1 | B3: Introduction
A5: Planned M&R is defined as dry dockings, (damage) repairs and modifications with a 'project approach'.
A7: Planned M&R projects need to be planned well before the start of activities. This plan should contain scope, planning and budget of the project.
A8: The planned M&R project plan should be prepared taking into consideration minimizing running M&R expenses during the period in between
A9: two special surveys.
A11: The general purpose of the planned M&R budget control tool is to give technical superintendents a tool to budget planned M&R projects before the
A12: execution of the project, and to control costs during the execution of the project. It should give guidance to monitor expenses and commitments
A13: thereto in comparison to the budget.
A14: By continious tracing of commitments and forecasts superintendents should be able to have complete insight in the financial progress of the
A15: planned M&R project. Any budget overruns can be anticipated at an early stage and corrective measures can be taken in time.
A17: In a broader sence, the finalized planned M&R project plans (including evaluations on actuals vs budget) should give Smit Lamnalco a tool to
A18: benchmark M&R projects in respect of costs and time.
A20: The planned M&R budget control tool consists of 3 main parts:
A21: 1 | B21: Planned M&R Project Plan
A22: 2 | B22: Planned M&R Daily Report
A23: 3 | B23: Planned M&R Project Plan - details per cost coding main group + damages & modifications
A25: The project plan contains general information and summerized financial information about the planned M&R project. This page is used for budget approval
A26: before the execution of the project. This page is also used to evaluate the project final results in comparison to the budget at the end of the planned M&R project.
A28: The daily report contains progress information and summerized financial information at a certain moment/period during the planned M&R project execution.
A29: The page is used to monitor the financial status and the progress of the project. Items which have financial impact or influence the progress of the project are reported on this page.
A31: The project plan details contains the corresponding details of each expense category. These pages gives the superintendent the possibility to budget and monitor expenses
A32: in detail. There are 'detail'-worksheets for all expense categories, which are further explained below:
A34: 1 | B34: Flag state-, class- and management, consumables, transportation
A35: 2 | B35: Ship’s hull, conservation.
A36: 3 | B36: Equipment and systems for crew and passengers.
A37: 4 | B37: Diesel engines, flexible couplings for DE’s, generators.
A38: 5 | B38: Ship propulsion and steering equipment.
A39: 6 | B39: Ship specific equipment.
A40: 7 | B40: Ship common systems deck department.
A41: 8 | B41: Ship common systems engine department.
A42: 9 | B42: Alongside repair and dry docking
A43: 10 | B43: Damages
A44: 11 | B44: Modifications
A46: Each expense category can be budgeted on the separate -worksheets. The 'detail'-worksheet per expense category should be filled
A47: with all individual work specifications (W.S.) budgeted. After budget approval, for each work specification the corresponding purchase order (at moment of issuing) and
A48: purchase invoice (at moment of receipt) can be reported. The technical superintendent can monitor the costs compared to the
A49: project budget and has an overview of the financial status of the project at any time.
A51: Work Variation Forms (WVF) are used to monitor additional and less work including the financial consequenses and influence on the work planning, if any.
A53: Repair of damages and modifications shall be budgeted and monitored separately from the planned M&R. Therefore separate
A54: detail'-worksheets are in place for these categories (damages and modifications).
A56: In general the following rules are used for input:
A57: Cells for input
A58: Fixed value input | C58: 0000
A59: Estimated value input | C59: 0000
A61: Note: Start with entering the project specific details, such as vessel name, dates, etc. in the yellow marked fields on the Planned M&R Project Plan page.
A63: 2 | B63: Planned M&R - Project Plan page
A65: Contact the financial department to obtain a Project no. This project number is used to allocate the actual project expenses in the accounting system.
A67: Based on a combination of Project no., Vessel ID, month and year of demobilisation each planned M&R project has an assigned reference ID.
A68: The planned M&R project ID reference in combination with the number of the sub category (1 to 11, see above) must be used by suppliers, and shall be included in the invoices.
A70: Explanatory notes in reference to the planned M&R project plan can be made in the remark field on line level.
A72: Amounts will be filled in the 'detail'-worksheets of the planned M&R budget control tool. Reference is made to item 3 below, M&R project plan - details.
A74: Applicant- , consent- and approval level will be adjusted, based on total amount of the project plan.
A76: This M&R project plan page is also to be used for additional authorization, required in case of an budget overrun of > 5%.
A78: 3 | B78: Details'-worksheets: Planned M&R Group 1 - 9, Group 10 Damages and Group 11 Modifications
A80: For the detailed planning and for cost control, the M&R project plan - 'detail'-worksheet (per Expense Category) is used.
A81: The totals per project plan expense category are linked to the corresponding totals in the M&R project plan page and Planned M&R Daily Report page.
A83: The M&R project plan should be filled out in USD. For the purchases in other currencies corresponding conversion rates can be filled in.
A85: After final approval of the budget, cost control is monitored by using the commitment, forecast and actual columns.
A86: Total commited: answers the question "when the project is stopped today what is the amount of money spent."
A87: Total forecast: answers the question "what is the total amount of money what we expect to spent by the end of the M&R project."
A88: Total actual: is the total amount booked in the ERP system.
A90: The final evaluation of actuals vs budget/forecast shall be made when all the work is completed.
A92: Consent/approval of the evaluation is in line with the authorization levels for the planned M&R project plan budget.
A94: The financial deptartment will accrue in the financial books the estimated actual costs still to be expected. This is determined from the difference
A95: between forecast/commitments and actual received and approved (= booked) purchase invoices.
A96: The finance dept will monitor actual purchase invoices in comparison to the accrual.
... A102: The explantory notes can be used to further explain the background and nature of the damage and the corresponding repair.

Sheet Planned M&R Project Plan
J1: FRM-OFF-04-Site Specific Novo-002
D2: BUDGET CONTROL TOOLS | J2: File 04 / Папка 04
J3: Retention 3 Year / Срок хранения 3 года
B6: Planned M&R Project Plan
B10: Name TSI-P : | H10: Project Plan Currency: | I10: USD
B11: Name Client Representative : | H11: Yard invoice currency: | I11: RUB
B13: Project nr.: | H13: EXCHANGE RATE TO CURRENCY
B14: Vessel ID nr - internal: | H14: EUR
H15: SGD
B16: Yard name: | H16: GBP | I16: 0
B17: Yard location: | I17: 0
B19: TIMELINES M&R | C19: PLANNED | D19: ACTUAL
B20: Date vessel demobilised:
B21: Start date yard:
B22: Date in dock:
B23: Date out dock:
B24: Finish date yard:
B25: Date vessel mobilised:
B26: Days out of service:
B29: Total Costs Planned Maintenance and Repair
B30: GROUP | C30: TITLE | H30: BUDGET | I30: COMMITTED | J30: FORECAST | K30: ACTUAL
B31: 0 | C31: Crewing and Victuals | H31: ='Planned M&R Daily Report'!H32 -> 0 | I31: ='Planned M&R Daily Report'!I32 -> 0 | J31: ='Planned M&R Daily Report'!J32 -> 0
B32: 1 | C32: Flag state-, class- and management, consumables, transportation | H32: ='Planned M&R Daily Report'!H33 -> 0 | I32: ='Planned M&R Daily Report'!I33 -> 0 | J32: ='Planned M&R Daily Report'!J33 -> 0 | K32: ='Planned M&R Daily Report'!K33 -> 0
B33: 2 | C33: Ship’s hull,conservation | H33: ='Planned M&R Daily Report'!H34 -> 0 | I33: ='Planned M&R Daily Report'!I34 -> 0 | J33: ='Planned M&R Daily Report'!J34 -> 0 | K33: ='Planned M&R Daily Report'!K34 -> 0
B34: 3 | C34: Equipment and systems for crew and passengers | H34: ='Planned M&R Daily Report'!H35 -> 0 | I34: ='Planned M&R Daily Report'!I35 -> 0 | J34: ='Planned M&R Daily Report'!J35 -> 0 | K34: ='Planned M&R Daily Report'!K35 -> 0
B35: 4 | C35: Diesel engines, flexible couplings for DE’s, generators | H35: ='Planned M&R Daily Report'!H36 -> 0 | I35: ='Planned M&R Daily Report'!I36 -> 0 | J35: ='Planned M&R Daily Report'!J36 -> 0 | K35: ='Planned M&R Daily Report'!K36 -> 0
B36: 5 | C36: Ship propulsion and steering equipment | H36: ='Planned M&R Daily Report'!H37 -> 0 | I36: ='Planned M&R Daily Report'!I37 -> 0 | J36: ='Planned M&R Daily Report'!J37 -> 0 | K36: ='Planned M&R Daily Report'!K37 -> 0
B37: 6 | C37: Ship specific equipment | H37: ='Planned M&R Daily Report'!H38 -> 0 | I37: ='Planned M&R Daily Report'!I38 -> 0 | J37: ='Planned M&R Daily Report'!J38 -> 0 | K37: ='Planned M&R Daily Report'!K38 -> 0
B38: 7 | C38: Ship common systems deck department | H38: ='Planned M&R Daily Report'!H39 -> 0 | I38: ='Planned M&R Daily Report'!I39 -> 0 | J38: ='Planned M&R Daily Report'!J39 -> 0 | K38: ='Planned M&R Daily Report'!K39 -> 0
B39: 8 | C39: Ship common systems engine department | H39: ='Planned M&R Daily Report'!H40 -> 0 | I39: ='Planned M&R Daily Report'!I40 -> 0 | J39: ='Planned M&R Daily Report'!J40 -> 0 | K39: ='Planned M&R Daily Report'!K40 -> 0
B40: 9 | C40: Alongside repair and dry docking | H40: ='Planned M&R Daily Report'!H41 -> 0 | I40: ='Planned M&R Daily Report'!I41 -> 0 | J40: ='Planned M&R Daily Report'!J41 -> 0 | K40: ='Planned M&R Daily Report'!K41 -> 0
B41: 10 | C41: Damages | H41: ='Planned M&R Daily Report'!H42 -> 0 | I41: ='Planned M&R Daily Report'!I42 -> 0 | J41: ='Planned M&R Daily Report'!J42 -> 0 | K41: ='Planned M&R Daily Report'!K42 -> 0
B42: 11 | C42: Modifications | H42: ='Planned M&R Daily Report'!H43 -> 0 | I42: ='Planned M&R Daily Report'!I43 -> 0 | J42: ='Planned M&R Daily Report'!J43 -> 0 | K42: ='Planned M&R Daily Report'!K43 -> 0
G43: TOTALS | H43: =SUM(H31:H42) -> 0 | I43: =SUM(I31:I42) -> 0 | J43: =SUM(J31:J42) -> 0 | K43: =SUM(K31:K42) -> 0
B46: Approved by TSI-P: | D46: Date: | G46: Signature: | H46: Approved by CM: | J46: Date: | K46: Signature:
B50: Approved by ROM: | D50: Date: | G50: Signature: | H50: Approved by RTM: | J50: Date: | K50: Signature:
B54: Approved by RMD: | D54: Date: | G54: Signature: | H54: Approved by CTO: | J54: Date: | K54: Signature:
B58: Approved by BOM: | D58: Date: | G58: Signature: | H58: Approved by BOM: | J58: Date: | K58: Signature:
B62: Approved by BOM: | D62: Date: | G62: Signature:

Sheet Planned M&R Daily Report
J1: FRM-OFF-04-Site Specific Novo-002
C2: BUDGET CONTROL TOOLS | J2: File 04 / Папка 04
J3: Retention 3 Year / Срок
J4: хранения 3 года
B7: Planned M&R Daily Report
B9: ='Planned M&R Project Plan'!B8:D8 -> 0
B11: Name TSI-P : | C11: ='Planned M&R Project Plan'!C10:D10 -> 0 | H11: Project Plan Currency: | I11: USD
B12: Name Client Representative : | C12: ='Planned M&R Project Plan'!C11:D11 -> 0 | H12: Yard invoice currency: | I12: ='Planned M&R Project Plan'!I11 -> RUB
B14: Project nr.: | C14: ='Planned M&R Project Plan'!C13:D13 -> 0 | H14: EXCHANGE RATE TO CURRENCY
B15: Vessel ID nr - internal: | C15: ='Planned M&R Project Plan'!C14:D14 -> 0 | H15: EUR | I15: ='Planned M&R Project Plan'!I14 -> 0
H16: SGD | I16: ='Planned M&R Project Plan'!I15 -> 0
B17: Yard name: | C17: ='Planned M&R Project Plan'!C16:D16 -> 0 | H17: GBP | I17: ='Planned M&R Project Plan'!I16 -> 0
B18: Yard location: | C18: ='Planned M&R Project Plan'!C17:D17 -> 0 | I18: ='Planned M&R Project Plan'!I17 -> 0
B20: TIMELINES M&R | C20: PLANNED | D20: ACTUAL
B21: Date vessel demobilised: | C21: ='Planned M&R Project Plan'!C20 -> 0
B22: Start date yard: | C22: ='Planned M&R Project Plan'!C21 -> 0
B23: Date in dock: | C23: ='Planned M&R Project Plan'!C22 -> 0
B24: Date out dock: | C24: ='Planned M&R Project Plan'!C23 -> 0
B25: Finish date yard: | C25: ='Planned M&R Project Plan'!C24 -> 0
B26: Date vessel mobilised: | C26: ='Planned M&R Project Plan'!C25 -> 0
B27: Days out of service: | C27: ='Planned M&R Project Plan'!C26 -> 0 | D27: ='Planned M&R Project Plan'!D26 -> 0
B30: Total Costs Planned Maintenance and Repair
B31: GROUP | C31: TITLE | H31: BUDGET | I31: COMMITTED | J31: FORECAST | K31: ACTUAL
B32: 0 | C32: Crewing and Victuals | H32: ='Group 0'!F151 -> 0 | I32: ='Group 0'!G151 -> 0 | J32: ='Group 0'!H151 -> 0 | K32: ='Group 0'!I151 -> 0
B33: 1 | C33: Flag state-, class- and management, consumables, transportation | H33: ='Group 1'!F97 -> 0 | I33: ='Group 1'!G97 -> 0 | J33: ='Group 1'!H97 -> 0 | K33: ='Group 1'!I97 -> 0
B34: 2 | C34: Ship’s hull,conservation | H34: ='Group 2'!F81 -> 0 | I34: ='Group 2'!G81 -> 0 | J34: ='Group 2'!H81 -> 0 | K34: ='Group 2'!I81 -> 0
B35: 3 | C35: Equipment and systems for crew and passengers | H35: ='Group 3'!F94 -> 0 | I35: ='Group 3'!G94 -> 0 | J35: ='Group 3'!H94 -> 0 | K35: ='Group 3'!I94 -> 0
B36: 4 | C36: Diesel engines, flexible couplings for DE’s, generators | H36: ='Group 4'!F60 -> 0 | I36: ='Group 4'!G60 -> 0 | J36: ='Group 4'!H60 -> 0 | K36: ='Group 4'!I60 -> 0
B37: 5 | C37: Ship propulsion and steering equipment | H37: ='Group 5'!F98 -> 0 | I37: ='Group 5'!G98 -> 0 | J37: ='Group 5'!H98 -> 0 | K37: ='Group 5'!I98 -> 0
B38: 6 | C38: Ship specific equipment | H38: ='Group 6'!F78 -> 0 | I38: ='Group 6'!G78 -> 0 | J38: ='Group 6'!H78 -> 0 | K38: ='Group 6'!I78 -> 0
B39: 7 | C39: Ship common systems deck department | H39: ='Group 7'!F75 -> 0 | I39: ='Group 7'!G75 -> 0 | J39: ='Group 7'!H75 -> 0 | K39: ='Group 7'!I75 -> 0
B40: 8 | C40: Ship common systems engine department | H40: ='Group 8'!F97 -> 0 | I40: ='Group 8'!G97 -> 0 | J40: ='Group 8'!H97 -> 0 | K40: ='Group 8'!I97 -> 0
B41: 9 | C41: Alongside repair and dry docking | H41: ='Group 9'!F60 -> 0 | I41: ='Group 9'!G60 -> 0 | J41: ='Group 9'!H60 -> 0 | K41: ='Group 9'!I60 -> 0
B42: 10 | C42: Damages | H42: ='Group 10 Damages'!F15 -> 0 | I42: ='Group 10 Damages'!G15 -> 0 | J42: ='Group 10 Damages'!H15 -> 0 | K42: ='Group 10 Damages'!I15 -> 0
B43: 11 | C43: Modifications | H43: ='Group 11 Modifications'!F15 -> 0 | I43: ='Group 11 Modifications'!G15 -> 0 | J43: ='Group 11 Modifications'!H15 -> 0 | K43: ='Group 11 Modifications'!I15 -> 0
G44: TOTALS | H44: =SUM(H32:H43) -> 0 | I44: =SUM(I32:I43) -> 0 | J44: =SUM(J32:J43) -> 0 | K44: =SUM(K32:K43) -> 0
B46: Daily Reporting / Remarks concerning: | H46: Period From: | J46: To:

Sheet Group 0
E1: Main Group 0 | F1: ='Planned M&R Project Plan'!B8 -> 0
A2: NO. | B2: W.S. | C2: W.V.F. | D2: P.O. | E2: DESCRIPTION | F2: BUDGET | G2: COMMITTED | H2: FORECAST | I2: ACTUAL | J2: REMARKS
A4: 0 | B4: Crewing and Victuals
A6: 00 | E6: Salaries Permanent Sea staff (at Costs)
E13: SubTotal | F13: =SUM(F7:F12) -> 0 | G13: =SUM(G7:G12) -> 0 | H13: =SUM(H7:H12) -> 0 | I13: =SUM(I7:I12) -> 0
A15: 01 | E15: Salaries Sea staff on Consolidated Pay (at Costs)
E22: SubTotal | F22: =SUM(F16:F21) -> 0 | G22: =SUM(G16:G21) -> 0 | H22: =SUM(H16:H21) -> 0 | I22: =SUM(I16:I21) -> 0
A24: 02 | E24: Salaries Subcontract Sea staff (at Costs)
E31: SubTotal | F31: =SUM(F25:F30) -> 0 | G31: =SUM(G25:G30) -> 0 | H31: =SUM(H25:H30) -> 0 | I31: =SUM(I25:I30) -> 0
A33: 03 | E33: Salaries Day rate Client Contract
E40: SubTotal | F40: =SUM(F34:F39) -> 0 | G40: =SUM(G34:G39) -> 0 | H40: =SUM(H34:H39) -> 0 | I40: =SUM(I34:I39) -> 0
A42: 04 | E42: Salaries Lump sum Client Contract
E49: SubTotal | F49: =SUM(F43:F48) -> 0 | G49: =SUM(G43:G48) -> 0 | H49: =SUM(H43:H48) -> 0 | I49: =SUM(I43:I48) -> 0
A51: 05 | E51: Disbursement Costs, Crew Medical
E58: SubTotal | F58: =SUM(F52:F57) -> 0 | G58: =SUM(G52:G57) -> 0 | H58: =SUM(H52:H57) -> 0 | I58: =SUM(I52:I57) -> 0
A60: 06 | E60: Travel
E61: Tickets on ferry and living in hotel
E102: SubTotal | F102: =SUM(F61:F101) -> 0 | G102: =SUM(G61:G101) -> 0 | H102: =SUM(H61:H101) -> 0 | I102: =SUM(I61:I101) -> 0
A104: 07 | E104: Training
E111: SubTotal | F111: =SUM(F105:F110) -> 0 | G111: =SUM(G105:G110) -> 0 | H111: =SUM(H105:H110) -> 0 | I111: =SUM(I105:I110) -> 0
A113: 08
E120: SubTotal | F120: =SUM(F114:F119) -> 0 | G120: =SUM(G114:G119) -> 0 | H120: =SUM(H114:H119) -> 0 | I120: =SUM(I114:I119) -> 0
A122: 09 | E122: Victuals
E149: SubTotal | F149: =SUM(F123:F148) -> 0 | G149: =SUM(G123:G148) -> 0 | H149: =SUM(H123:H148) -> 0 | I149: =SUM(I123:I148) -> 0
E151: Total Main Group 0 | F151: =SUM(F13,F22,F31,F40,F49,F58,F102,F111,F120,F149) -> 0 | G151: =SUM(G13,G22,G31,G40,G49,G58,G102,G111,G120,G149) -> 0 | H151: =SUM(H13,H22,H31,H40,H49,H58,H102,H111,H120,H149) -> 0 | I151: =SUM(I13,I22,I31,I40,I49,I58,I102,I111,I120,I149) -> 0

Sheet Group 1
E1: Main Group 1 | F1: ='Planned M&R Project Plan'!B8 -> 0
A2: NO. | B2: W.S. | C2: W.V.F. | D2: P.O. | E2: DESCRIPTION | F2: BUDGET | G2: COMMITTED | H2: FORECAST | I2: ACTUAL | J2: REMARKS
A4: 1 | B4: Flag state-, class- and management, consumables, transportation
A6: 10 | E6: Flag state and survey
E13: SubTotal | F13: =SUM(F7:F12) -> 0 | G13: =SUM(G7:G12) -> 0 | H13: =SUM(H7:H12) -> 0 | I13: =SUM(I7:I12) -> 0
A15: 11 | E15: Management, inspection, PMS system
E22: SubTotal | F22: =SUM(F16:F21) -> 0 | G22: =SUM(G16:G21) -> 0 | H22: =SUM(H16:H21) -> 0 | I22: =SUM(I16:I21) -> 0
A24: 12 | E24: Insurance
E31: SubTotal | F31: =SUM(F25:F30) -> 0 | G31: =SUM(G25:G30) -> 0 | H31: =SUM(H25:H30) -> 0 | I31: =SUM(I25:I30) -> 0
A33: 13 | E33: Communication expenses
E40: SubTotal | F40: =SUM(F34:F39) -> 0 | G40: =SUM(G34:G39) -> 0 | H40: =SUM(H34:H39) -> 0 | I40: =SUM(I34:I39) -> 0
A42: 14 | E42: Bunkers and lubricating oil
E49: SubTotal | F49: =SUM(F43:F48) -> 0 | G49: =SUM(G43:G48) -> 0 | H49: =SUM(H43:H48) -> 0 | I49: =SUM(I43:I48) -> 0
A51: 15 | E51: Engine Stores, including chemicals
E58: SubTotal | F58: =SUM(F52:F57) -> 0 | G58: =SUM(G52:G57) -> 0 | H58: =SUM(H52:H57) -> 0 | I58: =SUM(I52:I57) -> 0
A60: 16 | E60: Deck consumables
E67: SubTotal | F67: =SUM(F61:F66) -> 0 | G67: =SUM(G61:G66) -> 0 | H67: =SUM(H61:H66) -> 0 | I67: =SUM(I61:I66) -> 0
A69: 17 | E69: Accommodation inventory
E76: SubTotal | F76: =SUM(F70:F75) -> 0 | G76: =SUM(G70:G75) -> 0 | H76: =SUM(H70:H75) -> 0 | I76: =SUM(I70:I75) -> 0
A78: 18 | E78: Crew’s working gear, workshop / Store outfit incl. cleaning equipment
E85: SubTotal | F85: =SUM(F79:F84) -> 0 | G85: =SUM(G79:G84) -> 0 | H85: =SUM(H79:H84) -> 0 | I85: =SUM(I79:I84) -> 0
A87: 19 | E87: Port expenses, transportation- and logistics expenses
E95: SubTotal | F95: =SUM(F88:F94) -> 0 | G95: =SUM(G88:G94) -> 0 | H95: =SUM(H88:H94) -> 0 | I95: =SUM(I88:I94) -> 0
E97: Total Main Group 1 | F97: =SUM(F13,F22,F31,F40,F49,F58,F67,F76,F85,F95) -> 0 | G97: =SUM(G13,G22,G31,G40,G49,G58,G67,G76,G85,G95) -> 0 | H97: =SUM(H13,H22,H31,H40,H49,H58,H67,H76,H85,H95) -> 0 | I97: =SUM(I13,I22,I31,I40,I49,I58,I67,I76,I85,I95) -> 0

Sheet Group 2
E1: Main Group 2 | F1: ='Planned M&R Project Plan'!B8 -> 0
A2: NO. | B2: W.S. | C2: W.V.F. | D2: P.O. | E2: DESCRIPTION | F2: BUDGET | G2: COMMITTED | H2: FORECAST | I2: ACTUAL | J2: REMARKS
A4: 2 | B4: Ship’s hull,conservation
A6: 20 | E6: Hull structure
J11: Add
E29: SubTotal | F29: =SUM(F7:F28) -> 0 | G29: =SUM(G7:G28) -> 0 | H29: =SUM(H7:H28) -> 0 | I29: =SUM(I7:I28) -> 0
A31: 21 | E31: Tanks and void spaces
E40: SubTotal | F40: =SUM(F32:F39) -> 0 | G40: =SUM(G32:G39) -> 0 | H40: =SUM(H32:H39) -> 0 | I40: =SUM(I32:I39) -> 0
A42: 22 | E42: Hull outfitting
E51: SubTotal | F51: =SUM(F43:F50) -> 0 | G51: =SUM(G43:G50) -> 0 | H51: =SUM(H43:H50) -> 0 | I51: =SUM(I43:I50) -> 0
A53: 23 | E53: Cathodic protection (anodes, impressed current)
E60: SubTotal | F60: =SUM(F54:F59) -> 0 | G60: =SUM(G54:G59) -> 0 | H60: =SUM(H54:H59) -> 0 | I60: =SUM(I54:I59) -> 0
A62: 24 | E62: Cathodic protection internal. (anodes, anti-fouling)
E69: SubTotal | F69: =SUM(F63:F68) -> 0 | G69: =SUM(G63:G68) -> 0 | H69: =SUM(H63:H68) -> 0 | I69: =SUM(I63:I68) -> 0
A71: 25 | E71: Conservation (paint)
E79: SubTotal | F79: =SUM(F72:F78) -> 0 | G79: =SUM(G72:G78) -> 0 | H79: =SUM(H72:H78) -> 0 | I79: =SUM(I72:I78) -> 0
E81: Total Main Group 2 | F81: =SUM(F29,F40,F51,F60,F69,F79) -> 0 | G81: =SUM(G29,G40,G51,G60,G69,G79) -> 0 | H81: =SUM(H29,H40,H51,H60,H69,H79) -> 0 | I81: =SUM(I29,I40,I51,I60,I69,I79) -> 0

Sheet Group 3
E1: Main Group 3 | F1: ='Planned M&R Project Plan'!B8 -> 0
A2: NO. | B2: W.S. | C2: W.V.F. | D2: P.O. | E2: DESCRIPTION | F2: BUDGET | G2: COMMITTED | H2: FORECAST | I2: ACTUAL | J2: REMARKS
A4: 3 | B4: Equipment and systems for crew and passengers
A6: 30 | E6: Lifesaving, medical equipment, portable fire fighting equipment and personal protection
E12: SubTotal | F12: =SUM(F7:F11) -> 0 | G12: =SUM(G7:G11) -> 0 | H12: =SUM(H7:H11) -> 0 | I12: =SUM(I7:I11) -> 0
A14: 31 | E14: Accomodation, insulation, panels, bulkheads, doors, windows, port holes and skylights
E22: SubTotal | F22: =SUM(F15:F20) -> 0 | G22: =SUM(G15:G20) -> 0 | H22: =SUM(H15:H20) -> 0 | I22: =SUM(I15:I20) -> 0
A24: 32 | E24: Accomodation, internal deck covering, internal / external ladders, steDAXX, platforms, railings and gangways
E31: SubTotal | F31: =SUM(F25:F30) -> 0 | G31: =SUM(G25:G30) -> 0 | H31: =SUM(H25:H30) -> 0 | I31: =SUM(I25:I30) -> 0
A33: 33 | E33: Furniture, inventory, entertainment equipment
E38: SubTotal | F38: =SUM(F34:F37) -> 0 | G38: =SUM(G34:G37) -> 0 | H38: =SUM(H34:H37) -> 0 | I38: =SUM(I34:I37) -> 0
A40: 34 | E40: Galley, pantry, laundry equipment, provision plants
E47: SubTotal | F47: =SUM(F41:F46) -> 0 | G47: =SUM(G41:G46) -> 0 | H47: =SUM(H41:H46) -> 0 | I47: =SUM(I41:I46) -> 0
A49: 35 | E49: Transport equipment for provisions, stores and engine room equipment
E56: SubTotal | F56: =SUM(F50:F55) -> 0 | G56: =SUM(G50:G55) -> 0 | H56: =SUM(H50:H55) -> 0 | I56: =SUM(I50:I55) -> 0
A58: 36 | E58: Accomodation ventilation, air-conditioning, and heating system
E65: SubTotal | F65: =SUM(F59:F64) -> 0 | G65: =SUM(G59:G64) -> 0 | H65: =SUM(H59:H64) -> 0 | I65: =SUM(I59:I64) -> 0
A67: 37 | E67: Fresh water (FW) makers
E74: SubTotal | F74: =SUM(F68:F73) -> 0 | G74: =SUM(G68:G73) -> 0 | H74: =SUM(H68:H73) -> 0 | I74: =SUM(I68:I73) -> 0
A76: 38 | E76: Hydrophore salt and fresh water systems
E83: SubTotal | F83: =SUM(F77:F82) -> 0 | G83: =SUM(G77:G82) -> 0 | H83: =SUM(H77:H82) -> 0 | I83: =SUM(I77:I82) -> 0
A85: 39 | E85: Sewage system
E92: SubTotal | F92: =SUM(F86:F91) -> 0 | G92: =SUM(G86:G91) -> 0 | H92: =SUM(H86:H91) -> 0 | I92: =SUM(I86:I91) -> 0
E94: Total Main Group 3 | F94: =SUM(F12,F22,F31,F38,F47,F56,F65,F74,F83,F92) -> 0 | G94: =SUM(G12,G22,G31,G38,G47,G56,G65,G74,G83,G92) -> 0 | H94: =SUM(H12,H22,H31,H38,H47,H56,H65,H74,H83,H92) -> 0 | I94: =SUM(I12,I22,I31,I38,I47,I56,I65,I74,I83,I92) -> 0

Sheet Group 4
E1: Main Group 4 | F1: ='Planned M&R Project Plan'!B8 -> 0
A2: NO. | B2: W.S. | C2: W.V.F. | D2: P.O. | E2: DESCRIPTION | F2: BUDGET | G2: COMMITTED | H2: FORECAST | I2: ACTUAL | J2: REMARKS
A4: 4 | B4: Diesel engines, flexible couplings for DE’s, generators
A6: 40 | E6: Diesel engine(s) direct for propulsion
E13: SubTotal | F13: =SUM(F7:F12) -> 0 | G13: =SUM(G7:G12) -> 0 | H13: =SUM(H7:H12) -> 0 | I13: =SUM(I7:I12) -> 0
A15: 41 | E15: Auxiliary gen.set, diesel engine(s)
E22: SubTotal | F22: =SUM(F16:F21) -> 0 | G22: =SUM(G16:G21) -> 0 | H22: =SUM(H16:H21) -> 0 | I22: =SUM(I16:I21) -> 0
A24: 42 | E24: Generator(s) for main electric power production
E31: SubTotal | F31: =SUM(F25:F30) -> 0 | G31: =SUM(G25:G30) -> 0 | H31: =SUM(H25:H30) -> 0 | I31: =SUM(I25:I30) -> 0
A33: 43 | E33: Emergency / Harbour gen.set, diesel engine(s)
E40: SubTotal | F40: =SUM(F34:F39) -> 0 | G40: =SUM(G34:G39) -> 0 | H40: =SUM(H34:H39) -> 0 | I40: =SUM(I34:I39) -> 0
A42: 44 | E42: Emergency / Harbour gen.set, generator(s)
E49: SubTotal | F49: =SUM(F43:F48) -> 0 | G49: =SUM(G43:G48) -> 0 | H49: =SUM(H43:H48) -> 0 | I49: =SUM(I43:I48) -> 0
A51: 45 | E51: Flexible coupling(s), for diesel engine(s), generators and Fi-Fi pumDAXX
E58: SubTotal | F58: =SUM(F52:F57) -> 0 | G58: =SUM(G52:G57) -> 0 | H58: =SUM(H52:H57) -> 0 | I58: =SUM(I52:I57) -> 0
E60: Total Main Group 4 | F60: =SUM(F13,F22,F31,F40,F49,F58) -> 0 | G60: =SUM(G13,G22,G31,G40,G49,G58) -> 0 | H60: =SUM(H13,H22,H31,H40,H49,H58) -> 0 | I60: =SUM(I13,I22,I31,I40,I49,I58) -> 0

Sheet Group 5
E1: Main Group 5 | F1: ='Planned M&R Project Plan'!B8 -> 0
A2: NO. | B2: W.S. | C2: W.V.F. | D2: P.O. | E2: DESCRIPTION | F2: BUDGET | G2: COMMITTED | H2: FORECAST | I2: ACTUAL | J2: REMARKS
A4: 5 | B4: Ship propulsion and -steering equipment
A6: 50 | E6: Electric motor(s) for propulsion
E13: SubTotal | F13: =SUM(F7:F12) -> 0 | G13: =SUM(G7:G12) -> 0 | H13: =SUM(H7:H12) -> 0 | I13: =SUM(I7:I12) -> 0
A15: 51 | E15: Flexible coupling(s) for propulsion and drive system
E22: SubTotal | F22: =SUM(F16:F21) -> 0 | G22: =SUM(G16:G21) -> 0 | H22: =SUM(H16:H21) -> 0 | I22: =SUM(I16:I21) -> 0
A24: 52 | E24: Fixed pitch propeller(s)
E31: SubTotal | F31: =SUM(F25:F30) -> 0 | G31: =SUM(G25:G30) -> 0 | H31: =SUM(H25:H30) -> 0 | I31: =SUM(I25:I30) -> 0
A33: 53 | E33: Controllable pitch propeller(s)
E40: SubTotal | F40: =SUM(F34:F39) -> 0 | G40: =SUM(G34:G39) -> 0 | H40: =SUM(H34:H39) -> 0 | I40: =SUM(I34:I39) -> 0
A42: 54 | E42: Rudders) and steering gear
E49: SubTotal | F49: =SUM(F43:F48) -> 0 | G49: =SUM(G43:G48) -> 0 | H49: =SUM(H43:H48) -> 0 | I49: =SUM(I43:I48) -> 0
A51: 55 | E51: Propulsion thruster(s)
E60: SubTotal | F60: =SUM(F52:F56) -> 0 | G60: =SUM(G52:G56) -> 0 | H60: =SUM(H52:H58) -> 0 | I60: =SUM(I52:I58) -> 0
A62: 56 | E62: Waterjet(s)
E69: SubTotal | F69: =SUM(F63:F68) -> 0 | G69: =SUM(G63:G68) -> 0 | H69: =SUM(H63:H68) -> 0 | I69: =SUM(I63:I68) -> 0
A71: 57 | E71: Bow thruster(s)
E78: SubTotal | F78: =SUM(F72:F77) -> 0 | G78: =SUM(G72:G77) -> 0 | H78: =SUM(H72:H77) -> 0 | I78: =SUM(I72:I77) -> 0
A80: 58 | E80: Stern thruster(s)
E87: SubTotal | F87: =SUM(F81:F86) -> 0 | G87: =SUM(G81:G86) -> 0 | H87: =SUM(H81:H86) -> 0 | I87: =SUM(I81:I86) -> 0
A89: 59 | E89: Stabilizer system, bubble plant (manoeuvring in ice)
E96: SubTotal | F96: =SUM(F90:F95) -> 0 | G96: =SUM(G90:G95) -> 0 | H96: =SUM(H90:H95) -> 0 | I96: =SUM(I90:I95) -> 0
E98: Total Main Group 5 | F98: =SUM(F13,F22,F31,F40,F49,F60,F69,F78,F87,F96) -> 0 | G98: =SUM(G13,G22,G31,G40,G49,G60,G69,G78,G87,G96) -> 0 | H98: =SUM(H13,H22,H31,H40,H49,H60,H69,H78,H87,H96) -> 0 | I98: =SUM(I13,I22,I31,I40,I49,I60,I69,I78,I87,I96) -> 0

Sheet Group 6
E1: Main Group 6 | F1: ='Planned M&R Project Plan'!B8 -> 0
A2: NO. | B2: W.S. | C2: W.V.F. | D2: P.O. | E2: DESCRIPTION | F2: BUDGET | G2: COMMITTED | H2: FORECAST | I2: ACTUAL | J2: REMARKS
A4: 6 | B4: Ship specific equipment
A6: 60 | E6: Towing- and anchor handling equipment
E22: SubTotal | F22: =SUM(F7:F21) -> 0 | G22: =SUM(G7:G21) -> 0 | H22: =SUM(H7:H21) -> 0 | I22: =SUM(I7:I21) -> 0
A24: 61 | E24: Deck Crane(s)
E31: SubTotal | F31: =SUM(F25:F30) -> 0 | G31: =SUM(G25:G30) -> 0 | H31: =SUM(H25:H30) -> 0 | I31: =SUM(I25:I30) -> 0
A33: 62 | E33: System(s) for liquid cargo
E40: SubTotal | F40: =SUM(F34:F39) -> 0 | G40: =SUM(G34:G39) -> 0 | H40: =SUM(H34:H39) -> 0 | I40: =SUM(I34:I39) -> 0
A42: 63 | E42: Saturation diving equipment
E49: SubTotal | F49: =SUM(F43:F48) -> 0 | G49: =SUM(G43:G48) -> 0 | H49: =SUM(H43:H48) -> 0 | I49: =SUM(I43:I48) -> 0
A51: 64 | E51: Air diving equipment
E58: SubTotal | F58: =SUM(F52:F57) -> 0 | G58: =SUM(G52:G57) -> 0 | H58: =SUM(H52:H57) -> 0 | I58: =SUM(I52:I57) -> 0
A60: 65 | E60: ROV equipment
E67: SubTotal | F67: =SUM(F61:F66) -> 0 | G67: =SUM(G61:G66) -> 0 | H67: =SUM(H61:H66) -> 0 | I67: =SUM(I61:I66) -> 0
A69: 66 | E69: Other ship specific equipment
E76: SubTotal | F76: =SUM(F70:F75) -> 0 | G76: =SUM(G70:G75) -> 0 | H76: =SUM(H70:H75) -> 0 | I76: =SUM(I70:I75) -> 0
E78: Total Main Group 6 | F78: =SUM(F22,F31,F40,F49,F58,F67,F76) -> 0 | G78: =SUM(G22,G31,G40,G49,G58,G67,G76) -> 0 | H78: =SUM(H22,H31,H40,H49,H58,H67,H76) -> 0 | I78: =SUM(I22,I31,I40,I49,I58,I67,I76) -> 0

Sheet Group 7
E1: Main Group 7 | F1: ='Planned M&R Project Plan'!B8 -> 0
A2: NO. | B2: W.S. | C2: W.V.F. | D2: P.O. | E2: DESCRIPTION | F2: BUDGET | G2: COMMITTED | H2: FORECAST | I2: ACTUAL | J2: REMARKS
A4: 7 | B4: Ship common systems deck department
A6: 70 | E6: Navigation equipment
E12: SubTotal | F12: =SUM(F7:F11) -> 0 | G12: =SUM(G7:G11) -> 0 | H12: =SUM(H7:H11) -> 0 | I12: =SUM(I7:I11) -> 0
A14: 71 | E14: Communication equipment
E21: SubTotal | F21: =SUM(F15:F20) -> 0 | G21: =SUM(G15:G20) -> 0 | H21: =SUM(H15:H20) -> 0 | I21: =SUM(I15:I20) -> 0
A23: 72 | E23: Dynamic positioning (DP) equipment
E30: SubTotal | F30: =SUM(F24:F29) -> 0 | G30: =SUM(G24:G29) -> 0 | H30: =SUM(H24:H29) -> 0 | I30: =SUM(I24:I29) -> 0
A32: 73 | E32: Closed circuit TV systems
E39: SubTotal | F39: =SUM(F33:F38) -> 0 | G39: =SUM(G33:G38) -> 0 | H39: =SUM(H33:H38) -> 0 | I39: =SUM(I33:I38) -> 0
A41: 74 | E41: Anchor- and mooring equipment
E48: SubTotal | F48: =SUM(F42:F47) -> 0 | G48: =SUM(G42:G47) -> 0 | H48: =SUM(H42:H47) -> 0 | I48: =SUM(I42:I47) -> 0
A50: 75 | E50: Fire- and life boat alarm, firefighting- and wash down systems
E57: SubTotal | F57: =SUM(F51:F56) -> 0 | G57: =SUM(G51:G56) -> 0 | H57: =SUM(H51:H56) -> 0 | I57: =SUM(I51:I56) -> 0
A59: 76 | E59: Bilge- and Ballast systems, scupper pipes outside
E64: SubTotal | F64: =SUM(F60:F63) -> 0 | G64: =SUM(G60:G63) -> 0 | H64: =SUM(H60:H63) -> 0 | I64: =SUM(I60:I63) -> 0
A66: 77 | E66: Aeration- and sounding systems from tanks to deck
E73: SubTotal | F73: =SUM(F67:F72) -> 0 | G73: =SUM(G67:G72) -> 0 | H73: =SUM(H67:H72) -> 0 | I73: =SUM(I67:I72) -> 0
E75: Total Main Group 7 | F75: =SUM(F12,F21,F30,F39,F48,F57,F64,F73) -> 0 | G75: =SUM(G12,G21,G30,G39,G48,G57,G64,G73) -> 0 | H75: =SUM(H12,H21,H30,H39,H48,H57,H64,H73) -> 0 | I75: =SUM(I12,I21,I30,I39,I48,I57,I64,I73) -> 0

Sheet Group 8
E1: Main Group 8 | F1: ='Planned M&R Project Plan'!B8 -> 0
A2: NO. | B2: W.S. | C2: W.V.F. | D2: P.O. | E2: DESCRIPTION | F2: BUDGET | G2: COMMITTED | H2: FORECAST | I2: ACTUAL | J2: REMARKS
A4: 8 | B4: Ship common systems engine department
A6: 80 | E6: Fuel systems
A15: 81
A24: 82
E33: SubTotal | F33: =SUM(F25:F30) -> 0 | G33: =SUM(G25:G30) -> 0 | H33: =SUM(H25:H30) -> 0 | I33: =SUM(I25:I32) -> 0
A35: 83 | E35: Compressed air systems
A42: 84
E49: SubTotal | F49: =SUM(F43:F48) -> 0 | G49: =SUM(G43:G48) -> 0 | H49: =SUM(H43:H48) -> 0 | I49: =SUM(I43:I48) -> 0
A51: 85 | E51: Other ship common systems
E58: SubTotal | F58: =SUM(F52:F57) -> 0 | G58: =SUM(G52:G57) -> 0 | H58: =SUM(H52:H57) -> 0 | I58: =SUM(I52:I57) -> 0
A60: 86 | E60: Electric power distribution system, incl. cable installations
E68: SubTotal | F68: =SUM(F61:F67) -> 0 | G68: =SUM(G61:G67) -> 0 | H68: =SUM(H61:H67) -> 0 | I68: =SUM(I61:I67) -> 0
A70: 87 | E70: Lighting systems, incl. emergency lighting
E77: SubTotal | F77: =SUM(F71:F76) -> 0 | G77: =SUM(G71:G76) -> 0 | H77: =SUM(H71:H76) -> 0 | I77: =SUM(I71:I76) -> 0
A79: 88 | E79: Remote control systems for propulsion- and maneuvering equipment
E86: SubTotal | F86: =SUM(F80:F85) -> 0 | G86: =SUM(G80:G85) -> 0 | H86: =SUM(H80:H85) -> 0 | I86: =SUM(I80:I85) -> 0
A88: 89 | E88: Alarm- and monitoring and automation systems for machinery
E95: SubTotal | F95: =SUM(F89:F94) -> 0 | G95: =SUM(G89:G94) -> 0 | H95: =SUM(H89:H94) -> 0 | I95: =SUM(I89:I94) -> 0
E97: Total Main Group 8 | F97: =SUM(F13,F22,F33,F40,F49,F58,F68,F77,F86,F95) -> 0 | G97: =SUM(G13,G22,G33,G40,G49,G58,G68,G77,G86,G95) -> 0 | H97: =SUM(H13,H22,H33,H40,H49,H58,H68,H77,H86,H95) -> 0 | I97: =SUM(I13,I22,I33,I40,I49,I58,I68,I77,I86,I95) -> 0

Sheet Group 9
E1: Main Group 9 | F1: ='Planned M&R Project Plan'!B8 -> 0
A2: NO. | B2: W.S. | C2: W.V.F. | D2: P.O. | E2: DESCRIPTION | F2: BUDGET | G2: COMMITTED | H2: FORECAST | I2: ACTUAL | J2: REMARKS
A4: 9 | B4: Alongside repair and dry docking
A6: 90
A15: 91
A24: 92
E31: SubTotal | F31: =SUM(F25:F30) -> 0 | G31: =SUM(G25:G30) -> 0 | H31: =SUM(H25:H30) -> 0 | I31: =SUM(I25:I30) -> 0
A33: 93 | E33: Temporary covering and gear
E40: SubTotal | F40: =SUM(F34:F39) -> 0 | G40: =SUM(G34:G39) -> 0 | H40: =SUM(H34:H39) -> 0 | I40: =SUM(I34:I39) -> 0
A42: 94 | E42: Testing during / after docking
E49: SubTotal | F49: =SUM(F43:F48) -> 0 | G49: =SUM(G43:G48) -> 0 | H49: =SUM(H43:H48) -> 0 | I49: =SUM(I43:I48) -> 0
A51: 95 | E51: Delivery trip and trials
E58: SubTotal | F58: =SUM(F52:F57) -> 0 | G58: =SUM(G52:G57) -> 0 | H58: =SUM(H52:H57) -> 0 | I58: =SUM(I52:I57) -> 0
E60: Total Main Group 9 | F60: =SUM(F13,F22,F31,F40,F49,F58) -> 0 | G60: =SUM(G13,G22,G31,G40,G49,G58) -> 0 | H60: =SUM(H13,H22,H31,H40,H49,H58) -> 0 | I60: =SUM(I13,I22,I31,I40,I49,I58) -> 0

Sheet Group 10 Damages
E1: Group 10 Damages | F1: ='Planned M&R Project Plan'!B8 -> 0
A2: NO. | B2: W.S. | C2: W.V.F. | D2: P.O. | E2: DESCRIPTION | F2: BUDGET | G2: COMMITTED | H2: FORECAST | I2: ACTUAL | J2: REMARKS
A4: 10 | B4: Damages
A6: 100 | E6: Damages
E13: SubTotal | F13: =SUM(F7:F12) -> 0 | G13: =SUM(G7:G12) -> 0 | H13: =SUM(H7:H12) -> 0 | I13: =SUM(I7:I12) -> 0
E15: Total Group 10 Damages | F15: =SUM(F13) -> 0 | G15: =SUM(G13) -> 0 | H15: =SUM(H13) -> 0 | I15: =SUM(I13) -> 0

Sheet Group 11 Modifications
E1: Group 11 Modifications | F1: ='Planned M&R Project Plan'!B8 -> 0
A2: NO. | B2: W.S. | C2: W.V.F. | D2: P.O. | E2: DESCRIPTION | F2: BUDGET | G2: COMMITTED | H2: FORECAST | I2: ACTUAL | J2: REMARKS
A4: 11 | B4: Modifications
A6: 110 | E6: Modifications
E13: SubTotal | F13: =SUM(F7:F12) -> 0 | G13: =SUM(G7:G12) -> 0 | H13: =SUM(H7:H12) -> 0 | I13: =SUM(I7:I12) -> 0
E15: Total Group 11 Modifications | F15: =SUM(F13) -> 0 | G15: =SUM(G13) -> 0 | H15: =SUM(H13) -> 0 | I15: =SUM(I13) -> 0

Sheet W.S. Overview
B1: Overview work specifications and prices
A5: ='Planned M&R Project Plan'!B8 -> 0
A7: Planned M&R execution date:
A8: Name Yard: | F8: ='Planned M&R Project Plan'!C16 -> 0
A9: Estimated continuous running days:
A11: NO. | B11: W.S. | C11: Y | D11: S | E11: Brief description of the work | G11: Estimated price | H11: Quoted price | I11: Related requisition | J11: Related P.O. | K11: Executed by | L11: Remarks
A12: 1
A13: =A12+1 -> 2
A14: 2
A15: =A14+1 -> 3
A16: 3
A17: =A16+1 -> 4
A18: 4
A19: =A18+1 -> 5
A20: 5
A21: =A20+1 -> 6
A22: 6
A23: =A22+1 -> 7
A24: 7
A25: =A24+1 -> 8
A26: 8
A27: =A26+1 -> 9
A28: 9
A29: =A28+1 -> 10
A30: 10
A31: =A30+1 -> 11
A32: 11
A33: =A32+1 -> 12
A34: 12
A35: =A34+1 -> 13
A36: 13
A37: =A36+1 -> 14
A38: 14
A39: =A38+1 -> 15
A40: 15
A41: =A40+1 -> 16
A42: 16
A43: =A42+1 -> 17
A44: 17
A45: =A44+1 -> 18
A46: 18
A47: =A46+1 -> 19
A48: 19
A49: =A48+1 -> 20
A50: 20
A51: =A50+1 -> 21
A52: 21
A53: =A52+1 -> 22
A54: 22
A55: =A54+1 -> 23
A56: 23
A57: =A56+1 -> 24
A58: 24
A59: =A58+1 -> 25
A60: 25
A61: =A60+1 -> 26
A62: 26
A63: =A62+1 -> 27
A64: 27
A65: =A64+1 -> 28
A66: 28
A67: =A66+1 -> 29
A68: 29
A69: =A68+1 -> 30
A70: 30
A71: =A70+1 -> 31
A72: 31
A73: =A72+1 -> 32
A74: 32
A75: =A74+1 -> 33
A76: 33
A77: =A76+1 -> 34
A78: 34
A79: =A78+1 -> 35
A80: 35
A81: =A80+1 -> 36
A82: 36
A83: =A82+1 -> 37
A84: 37
A85: =A84+1 -> 38
A86: 38
A87: =A86+1 -> 39
A88: 39
A89: =A88+1 -> 40
A90: 40
A91: =A90+1 -> 41
A92: 41
A93: =A92+1 -> 42
A94: 42
A95: =A94+1 -> 43
A96: 43
A97: =A96+1 -> 44
A98: 44
A99: =A98+1 -> 45
A100: 45
A101: =A100+1 -> 46
A102: 46
A103: =A102+1 -> 47
A104: 47
A105: =A104+1 -> 48
...

Sheet Req._P.O. Overview
C1: Spares Requirements for Dry Docking
A5: ='Planned M&R Project Plan'!B8 -> 0
A7: Planned M&R execution date:
A9: Req No | B9: Related W.S. No | C9: Parts Description | D9: P.O. | E9: Estimated amount | F9: Fixed amount | G9: Remarks from purchasing
D97: =SUM(D10:D96) -> 0
